{
  "book": "Salmernes Bog",
  "abbreviation": "Sl",
  "chapter": 124,
  "version": 1492552800000,
  "verses": [
    {
      "text": "Valfartssang. Af David.Hvis ikke JHVH havde været med os– sådan skal Israel sige –",
      "number": 1
    },
    {
      "text": "hvis ikke JHVH havde været med os,dengang mennesker rejste sig mod os,",
      "number": 2
    },
    {
      "text": "så havde de opslugt os levendei deres flammende vrede mod os,",
      "number": 3
    },
    {
      "text": "så var vandene skyllet over os,en vandstrøm var gået over vor hals,",
      "number": 4
    },
    {
      "text": "så var de gået over vor hals,de brusende vande!",
      "number": 5
    },
    {
      "text": "Lovet være JHVHsom ikke gav os til bytte for deres tænder!",
      "number": 6
    },
    {
      "text": "Vort liv undslap som en fuglaf fuglefængernes fælde.Fælden blev knust,og vi undslap.",
      "number": 7
    },
    {
      "text": "Vor hjælp er i JHVHs navn,hans som skabte himmel og jord.",
      "number": 8
    }
  ],
  "titles": [
    {
      "text": "Overskrift",
      "verse": 1
    },
    {
      "text": "Hvis ikke JHVH havde været med os",
      "verse": 2
    },
    {
      "text": "Lovet være JHVH som var med os",
      "verse": 6
    }
  ],
  "footnotes": [
    {
      "text": "Se note til Sl 120,1.",
      "type": "E",
      "verse": 1,
      "position": 13
    },
    {
      "text": "Sætningen kan også oversættes: >>Hvis ikke det var JHVH, der havde været med os<<.",
      "type": "T",
      "verse": 1,
      "position": 56
    },
    {
      "text": "Grundteksten har singularis: *ʔādām*, der må opfattes kollektivt.",
      "type": "T",
      "verse": 2,
      "position": 51
    },
    {
      "text": "Grundteksten har: *nefeš*, hvis oprindelige betydning ofte opgives som: >>hals<<. Grundbetydningen i GT er dog: >>sjæl<<. Det oversættes ofte: >>liv<<. Her oversættes det ofte: >>os<<.",
      "type": "E",
      "verse": 4,
      "position": 67
    },
    {
      "text": "Kan også oversættes: >>velsignet<<.",
      "type": "T",
      "verse": 6,
      "position": 5
    },
    {
      "text": "Ordret: >>sjæl<<.",
      "type": "T",
      "verse": 7,
      "position": 8
    }
  ]
}