{
  "book": "Salmernes Bog",
  "abbreviation": "Sl",
  "chapter": 14,
  "version": 1504476000000,
  "verses": [
    {
      "text": "Til korlederen. Af David.En tåbe siger i sit hjerte: >>Der er ingen Gud<<.De udfører fordærvelig, afskyelig gerning,der er ingen der gør godt.",
      "number": 1
    },
    {
      "text": "JHVH skuede ned fra himlenpå menneskene,for at se om der var en forstandig,en der søgte Gud.",
      "number": 2
    },
    {
      "text": "De er alle kommet på afveje,alle er fordærvede,ingen gør godt,end ikke en eneste.",
      "number": 3
    },
    {
      "text": "Mon de ikke ved det, alle de der begår synd,de der æder mit folk, som åd de brød?de kaldte ikke på JHVH.",
      "number": 4
    },
    {
      "text": "Da skal de gribes af stor rædsel,for Gud er med en retfærdigs slægt.",
      "number": 5
    },
    {
      "text": "Gør blot den hjælpeløses plan til skamme,for JHVH er dog hans tilflugt.",
      "number": 6
    },
    {
      "text": "Gid{T: Ordret: >>hvem giver<<, men det er en almindelig ønskeformel.} Israels frelse må komme fra Zion!Når JHVH vender sit folks lod,{E: Ordet *šᵊvût* er omdiskuteret. Tidligere mente man det er afledt af roden * šbh* (>>tage til fange<<), altså: >>fangenskab<<. Nu peges der oftest på roden *šwb* (egtl.: >>vende tilbage<<), her: >>lod<< eller evt. >>ændre forholdene/situationen<<.}skal Jakob juble, Israel skal glæde sig.",
      "number": 7
    }
  ],
  "titles": [
    {
      "text": "Overskrift",
      "verse": 1
    },
    {
      "text": "Klage over menneskers fordærvede tilstand",
      "verse": 2
    },
    {
      "text": "Gud er dommer og frelser",
      "verse": 4
    },
    {
      "text": "Bøn om frelse",
      "verse": 7
    }
  ],
  "footnotes": [
    {
      "text": "Betydningen af *lamnaṣṣēₐḥ* er usikker, men det er sandsynligvis afledt af et verbum der betyder >>dirigere<<.",
      "type": "E",
      "verse": 1,
      "position": 15
    },
    {
      "text": "Ordret: >>Adams børn/menneskes børn<<.",
      "type": "T",
      "verse": 2,
      "position": 40
    },
    {
      "text": "Perfektiv skal oftest oversættes ved fortid, men her er den forstået som udtryk for vished om det, der vil ske. Ellers skal der oversættes: >>Da var de grebet af stor rædsel<<.",
      "type": "E",
      "verse": 5,
      "position": 33
    }
  ]
}