{
  "book": "Salmernes Bog",
  "abbreviation": "Sl",
  "chapter": 69,
  "translation": 100,
  "contributors": [
    {
      "type": "Oversættelse",
      "name": "Jørgen Bækgaard Thomsen"
    },
    {
      "type": "Litterært tjek",
      "name": "Trine Tøndering"
    },
    {
      "type": "Eksegetisk bearbejdning",
      "name": "Nicolai Winther-Nielsen"
    }
  ],
  "verses": [
    {
      "number": 1,
      "text": "Til korlederen. Al-shoshannim. Af David.",
      "title": "Overskrift",
      "footnotes": [
        {
          "text": "E: Betydningen af *lamnaṣṣēₐḥ* er usikker, men det er sandsynligvis afledet af et verbum der betyder »dirigere«.",
          "position": 15
        },
        {
          "text": "E: Formodentlig en melodioplysning. Ordets betydning er ukendt, men synes at have sammenhæng med ordet for »lilje« (evt. »efter liljerne«).",
          "position": 30
        }
      ],
      "version": 1646002800000
    },
    {
      "number": 2,
      "text": "\fFrels mig, Gud,\ffor vandet når mig til halsen,",
      "title": "Klage i nød og bøn om frelse",
      "footnotes": [
        {
          "text": "T: Ordret: »sjælen«.",
          "position": 47
        }
      ],
      "version": 1646002800000
    },
    {
      "number": 3,
      "text": "\fjeg er sunket i dybets dynd,\fhvor der ikke er fodfæste.\fJeg er kommet i dybt vand,\fog en strøm skyller over mig.",
      "footnotes": [
        {
          "text": "T: Ordet: »vandes dybde«.",
          "position": 83
        }
      ],
      "version": 1646002800000
    },
    {
      "number": 4,
      "text": "\fJeg er udmattet af at råbe,\fmin strube er hæs,\fmine øjne er udmattede,\fidet jeg venter på min Gud.",
      "footnotes": [
        {
          "text": "E: Ofte vælger man at følge Septuaginta og andre gamle oversættelser der i stedet for participiet i pi’el *mᵊyaḥēl* (»idet jeg venter«) har vokaliseret som præposition og infinitiv: *miyyaḥēl*: »af at vente«.",
          "position": 87
        }
      ],
      "version": 1646002800000
    },
    {
      "number": 5,
      "text": "\fFlere end hår på mit hoved\fer de som hader mig uden grund.\fTalrige er de blevet som søger at udrydde mig,\fmine løgnagtige fjender.\fDet jeg ikke har røvet,\fdet skal jeg alligevel bringe tilbage.",
      "footnotes": [
        {
          "text": "T: Kan også oversættes: »mægtige«.",
          "position": 67
        }
      ],
      "version": 1646002800000
    },
    {
      "number": 6,
      "text": "\fGud, du har kendt min tåbelighed,\fog min skyld var ikke skjult for dig.",
      "version": 1646002800000
    },
    {
      "number": 7,
      "text": "\fLad ikke dem der håber på dig, blive gjort til skamme ved mig,\fHerre, Hærskarers JHVHv!\fLad ikke dem som søger dig, blive forhånede ved mig,\fIsraels Gud.",
      "footnotes": [
        {
          "text": "T: Ordret: »Må ikke de …«.",
          "position": 13
        },
        {
          "text": "T: I ældre tid uoversat: »Zebaoth«",
          "position": 81
        }
      ],
      "version": 1646002800000
    },
    {
      "number": 8,
      "text": "\fFor på grund af dig har jeg båret hån,\fskændsel har dækket mit ansigt.",
      "version": 1646002800000
    },
    {
      "number": 9,
      "text": "\fJeg er fremmedgjort for mine brødre\fog en udlænding for min moders sønner.",
      "version": 1646002800000
    },
    {
      "number": 10,
      "text": "\fFor nidkærhed for dit hus har fortæret mig,\fog spot fra dem som spotter dig, er faldet på mig.",
      "version": 1646002800000
    },
    {
      "number": 11,
      "text": "\fJeg, min sjæl, græd under faste,\fmen det blev til hån for mig.",
      "footnotes": [
        {
          "text": "E: Sætningen er knudret og omdiskuteret. Ordret: »Jeg græd i faste, min sjæl«. Meningen kan være som her i oversættelsen. Andre muligheder er: »Jeg græd og fastede for min sjæl«, eller: »Jeg græd og fastede i mit inderste«.",
          "position": 33
        }
      ],
      "version": 1646002800000
    },
    {
      "number": 12,
      "text": "\fJeg brugte sæk som min klædning,\fjeg blev genstand for spottetale for dem.",
      "version": 1646002800000
    },
    {
      "number": 13,
      "text": "\fDe som sidder i porten, vil snakke om mig,\fog drankernes viser handler om mig.",
      "footnotes": [
        {
          "text": "E: Der er ikke noget verbum i denne linje der er tæt knyttet til den foregående, og verbet dér gælder også for denne linje. Ordret: »og drankernes viser (taler om mig)«.",
          "position": 79
        }
      ],
      "version": 1646002800000
    },
    {
      "number": 14,
      "text": "\fMen jeg - min bøn er til dig,\fJHVHv, om en velbehagelig tid,\fGud, i din store nåde:\fBønhør mig for din frelses sandheds skyld!",
      "footnotes": [
        {
          "text": "N: nåde",
          "position": 83
        },
        {
          "text": "T: Grundtekstens *ʔemet* har ikke nogen nøjagtig ækvivalent på dansk. Ofte skal det oversættes »sandhed«. Det betegner det der står urokkeligt fast, og er et vigtigt ord i pagtssproget, hvor det ofte må oversættes: »trofasthed«.",
          "position": 120
        }
      ],
      "version": 1646002800000
    },
    {
      "number": 15,
      "text": "\fRed mig op af dyndet så jeg ikke synker,\flad mig blive reddet fra dem der hader mig, og fra vandenes dyb!",
      "version": 1646002800000
    },
    {
      "number": 16,
      "text": "\fLad ikke vandstrømmene skylle over mig,\fog lad ikke dybet opsluge mig,\fog lad ikke en brønd lukke sin mund over mig!",
      "footnotes": [
        {
          "text": "T: Ordet: »brønd« er her muligvis brugt som synonym for »grav«",
          "position": 92
        }
      ],
      "version": 1646002800000
    },
    {
      "number": 17,
      "text": "\fSvar mig, JHVHv, for din nåde er god,\fvend dit ansigt til mig efter din store barmhjertighed!",
      "version": 1646002800000
    },
    {
      "number": 18,
      "text": "\fOg skjul ikke dit ansigt for din tjener,\ffor jeg er i nød, skynd dig, svar mig!",
      "version": 1646002800000
    },
    {
      "number": 19,
      "text": "\fKom nær til mig, genløs,\fudfri mig for mine fjenders skyld!",
      "footnotes": [
        {
          "text": "T: Ordret: »til min sjæl«.",
          "position": 17
        }
      ],
      "version": 1646002800000
    },
    {
      "number": 20,
      "text": "\fDu har kendt min hån\fog min skam og min skændsel,\falle der bekriger mig, har du for øje.",
      "version": 1646002800000
    },
    {
      "number": 21,
      "text": "\fHån har knust mit hjerte,\fjeg blev svag.\fJeg ventede på medynk, men der var ingen,\fog på trøstere, men jeg fandt ikke nogen.",
      "footnotes": [
        {
          "text": "T: Betydningen af verbet *nwš*, der kun forekommer her i GT, er usikker. Andre foreslår: »kan ikke læges/er fortvivlet«.",
          "position": 41
        }
      ],
      "version": 1646002800000
    },
    {
      "number": 22,
      "text": "\fDe gav mig gift som føde\fog for min tørst gav de mig eddike at drikke.",
      "version": 1646002800000
    },
    {
      "number": 23,
      "text": "\fLad deres bord foran dem blive til en fælde\fog til en snare for sorgløse.",
      "title": "Bøn om Guds straf over fjenderne",
      "footnotes": [
        {
          "text": "E: Oversættelsen og forståelsen af linjen er usikker og omdiskuteret. Grundteksten har *wᵊlišlômîm*, som betyder »og … for fred«, men »fred« står i pluralis. Meningen kan være: »dem som har fred/sikkerhed«, som jeg har valgt at gengive: »sorgløse«. Denne pluralis findes kun tre steder i GT, og alle tre steder er der en række rettelsesforslag. Den mindst indgribende her er at indføje et *h*: *wᵊlišlômēhem*: »og (til en snare) i deres sorgløshed«. De gamle oversættelser har åbenbart læst: *ûlᵊšillômîm*: »og (til en snare) som gengæld«. Targum har læst: *wᵊšalmēhem*: »og deres offerfester (til en snare)«.",
          "position": 74
        }
      ],
      "version": 1646002800000
    },
    {
      "number": 24,
      "text": "\fLad deres øjne formørkes så de ikke ser,\fog deres lænder skal altid vakle!",
      "version": 1646002800000
    },
    {
      "number": 25,
      "text": "\fUdøs din harme over dem,\fog din vredes glød skal nå dem!",
      "version": 1646002800000
    },
    {
      "number": 26,
      "text": "\fDeres lejr skal blive øde,\fingen skal bo i deres telte.",
      "version": 1646002800000
    },
    {
      "number": 27,
      "text": "\fFor den som du har slået, forfølger de,\fog de øger smerten hos dem som du har såret.",
      "footnotes": [
        {
          "text": "E: Grundteksten har: *kî-ʔattāʰ*: »for du, ((den) som du har slået)«. Som regel følger man de gamle oversættelser og læser: *kî-ʔēt*: »for den« (som her). I konsonantteksten er det blot et enkelt *h*, der må slettes.",
          "position": 8
        },
        {
          "text": "E: Grundteksten har: »de fortæller til smerten hos dem, som du har såret«. Det kan være en eksemplificering af snakken i porten (v.13), om end brugen af præpositionen *ʔel* (»til«)i denne forbindelse er sjælden og uklar. Man må i givet fald oversætte ved: »om«, men det er tvivlsomt, om *ʔel* faktisk kan betyde »om«. Som regel følger man Septuaginta og læser: *yispāyû* (»de øger«) i stedet for *yᵊsappērû*",
          "position": 51
        }
      ],
      "version": 1646002800000
    },
    {
      "number": 28,
      "text": "\fLæg skyld til deres skyld,\fog lad dem ikke komme ind i din retfærdighed!",
      "version": 1646002800000
    },
    {
      "number": 29,
      "text": "\fLad dem blive slettet af de levendes bog,\fog lad dem ikke blive optegnet med de retfærdige!",
      "version": 1646002800000
    },
    {
      "number": 30,
      "text": "\fMen jeg - hjælpeløs og med smerte -\flad din frelse, Gud, beskytte mig.",
      "version": 1646002800000
    },
    {
      "number": 31,
      "text": "\fJeg vil lovprise Guds navn med sang,\fog jeg vil ophøje ham med tak.",
      "title": "Lovsang og tillid",
      "version": 1646002800000
    },
    {
      "number": 32,
      "text": "\fOg det vil behage JHVH mere end en okse,\fen ungtyr med horn og klove.",
      "version": 1646002800000
    },
    {
      "number": 33,
      "text": "\fDe ydmyge har set, de skal glæde sig,\fde, som søger Gud - og jeres hjerte skal live op!",
      "footnotes": [
        {
          "text": "T: Kan også oversættes: »elendige«.",
          "position": 10
        },
        {
          "text": "E: Verbet *rāˀû* (»har set/så«) er sætningens første ord i grundteksten. Ofte retter man vokaliseringen til imperativ: *rᵊˀû*: »Se! (De ydmyge skal glæde sig)«, eller man følger Septuaginta og læser jussiv: *jirᵊˀû*: »Lad (de ydmyge) se, (de skal glæde sig)«.",
          "position": 19
        }
      ],
      "version": 1646002800000
    },
    {
      "number": 34,
      "text": "\fFor JHVH hører på fattige\fog foragtede ikke sine fangne.",
      "version": 1646002800000
    },
    {
      "number": 35,
      "text": "\fHimmel og jord skal lovprise ham,\fhave og alt hvad der rører sig i dem!",
      "version": 1646002800000
    },
    {
      "number": 36,
      "text": "\fFor Gud vil frelse Zion\fog opbygge Judas byer,\fog de skal bo der og eje det,",
      "version": 1646002800000
    },
    {
      "number": 37,
      "text": "\fog hans tjeneres efterkommere skal arve det,\fog de som elsker hans navn, skal bo i det.",
      "footnotes": [
        {
          "text": "T: Ordret: »sæd«.",
          "position": 30
        }
      ],
      "version": 1646002800000
    }
  ]
}