{
  "book": "Salmernes Bog",
  "abbreviation": "Sl",
  "chapter": 8,
  "translation": 100,
  "contributors": [
    {
      "type": "Oversættelse",
      "name": "Jørgen Bækgaard Thomsen"
    },
    {
      "type": "Eksegetisk bearbejdning",
      "name": "Christian Højgaard"
    },
    {
      "type": "Eksegetisk layout",
      "name": "Mikkel Kølkær"
    }
  ],
  "verses": [
    {
      "number": 1,
      "text": "\fTil korlederen;\t\tal-ha-gittit;\ten salme af David.",
      "title": "Overskrift",
      "footnotes": [
        {
          "text": "*lamnaṣṣēₐḥ* er omdiskuteret, men substantivet må afledes af et verbum *nṣḥ*, der betyder »lede, dirigere«.",
          "type": "E",
          "position": 15
        },
        {
          "text": "Det vides ikke hvad der er ment med dette udtryk; det kan både være en melodiangivelse og en instrumentbetegnelse.",
          "type": "T",
          "position": 30
        }
      ],
      "version": 1666562400000
    },
    {
      "number": 2,
      "text": "\fJHVHv, vor Herre!\f\t\t\tHvor herligt er dit navn over hele jorden,\f\t\t\tdu som udbreder din majestæt over himlene!",
      "title": "David lovpriser skaberens herlighed",
      "footnotes": [
        {
          "text": "*tᵊnāʰ* er omdiskuteret. Det ser ud som imperativ af *ntn* »giv!«, men i sammenhængen kan det opfattes som kortform for infinitiven.",
          "type": "E",
          "position": 83
        }
      ],
      "version": 1666562400000
    },
    {
      "number": 3,
      "text": "\f\t\tAf spædes og diendes mund har du grundlagt et værn mod dine modstandere\f\t\t\tfor at standse fjenden og den som vil hævne sig.",
      "footnotes": [
        {
          "text": "*ʕōz* betyder oftest »magt, styrke«, men dernæst også »fæstning, bolværk«. Endelig kan det betyde »hæder, lovprisning, lovsang«, som det er forstået i LXX, jf. Matt 21,16. Sammenhængen her tyder på »værn«.",
          "type": "E",
          "position": 53
        },
        {
          "text": "*lᵊmaʕan* betyder ordret »for … skyld«, men oversættes her ofte »mod«.",
          "type": "T",
          "position": 74
        }
      ],
      "version": 1666562400000
    },
    {
      "number": 4,
      "text": "\f\tNår jeg ser din himmel, dine fingres gerninger,\f\t\t\tmånen og stjernerne,\t\t\t\tsom du anbragte,",
      "title": "I særdeleshed prises Guds godhed mod mennesket, som han satte til hersker over jorden",
      "version": 1666562400000
    },
    {
      "number": 5,
      "text": "\f\t\thvad er da et menneske\t\t\t\tat du husker på det;\f\t\t\tet menneskebarn\t\t\t\tat du tager dig af det?",
      "version": 1666562400000
    },
    {
      "number": 6,
      "text": "\f\t\t\t\t\t\tDu har gjort det kun lidt ringere end Gud;\f\t\t\t\t\t\t\tdu kronede det med ære og herlighed.",
      "footnotes": [
        {
          "text": "Oversættes oftest »englene« (således LXX), jf. Hebr 2,7.",
          "type": "T",
          "position": 48
        }
      ],
      "version": 1666562400000
    },
    {
      "number": 7,
      "text": "\f\t\t\t\t\tDu gør det til hersker over dine hænders gerninger;\f\t\t\t\t\t\tdu har lagt alting under dets fødder:",
      "version": 1666562400000
    },
    {
      "number": 8,
      "text": "\f\t\t\t\t\t\t\tFår og okser, dem alle sammen,\f\t\t\t\t\t\t\t\tja, også markens dyr,",
      "version": 1666562400000
    },
    {
      "number": 9,
      "text": "\f\t\t\t\t\t\t\tfuglene under himlen\t\t\t\t\t\t\t\t\tog fiskene i havet,\f\t\t\t\t\t\t\t\tdet som færdes ad havets stier.",
      "version": 1666562400000
    },
    {
      "number": 10,
      "text": "\fJHVHv, vor Herre!\f\tHvor herligt er dit navn over hele jorden!",
      "title": "Lovprisning",
      "version": 1666562400000
    }
  ]
}