{
  "book": "Zakarias' Bog",
  "abbreviation": "Zak",
  "chapter": 10,
  "version": 1472594400000,
  "authors": [
    {
      "name": "Christian Højgaard",
      "type": "translation"
    },
    {
      "name": "Trine Tøndering",
      "type": "literary check"
    }
  ],
  "verses": [
    {
      "text": "\fBed JHVH om regn på tidspunktet for den sene regn.\fJHVH laver lyn;\fhan giver dem regnskyl\fog enhver korn på marken.",
      "number": 1
    },
    {
      "text": "\fFor husguderne taler fordærv;\fspåmændene ser falske syner.\fDe tyder uduelige drømme;\fmed tomhed trøster de.\fDerfor er de i nød,\ffor der er ingen hyrde.",
      "number": 2
    },
    {
      "text": "\fImod hyrderne er min vrede opflammet;\fbukkene vil jeg hjemsøge.\fFor Hærskarers JHVHv har besøgt sin hjord, Judas hus,\fog gjort dem til sin prægtige hest i krigen.",
      "number": 3
    },
    {
      "text": "\fDerfra skal hjørnesten og teltpløk udgå,\fkrigsbuen og enhver hersker.",
      "number": 4
    },
    {
      "text": "\fDe skal være som krigere,\fder tramper i gadens mudder i krigen.\fDe skal kæmpe,\ffor JHVH vil være med dem.\fDe som rider på heste, skal blive til skamme.",
      "number": 5
    },
    {
      "text": "\fJeg vil styrke Judas hus;\fJosefs hus vil jeg frelse.\fJeg vil føre dem hjem,\ffor jeg har forbarmet mig over dem,\fog det skal blive, som om jeg ikke havde afvist dem.\fFor jeg er JHVH deres Gud;\fjeg vil bønhøre dem.",
      "number": 6
    },
    {
      "text": "\fEfraim skal blive som en kriger;\fderes hjerte skal juble som beruset.\fDeres børn skal se det og juble;\fderes hjerte skal råbe af fryd over JHVH.",
      "number": 7
    },
    {
      "text": "\fJeg vil fløjte ad dem og samle dem,\ffor jeg har løskøbt dem.\fDe skal blive talrige,\fligesom de var talrige.",
      "number": 8
    },
    {
      "text": "\fJeg vil så dem blandt folkeslagene;\fi det fjerne skal de huske på mig.\fDe og deres børn skal leve,\fog de skal vende hjem.",
      "number": 9
    },
    {
      "text": "\fJeg vil føre dem tilbage fra Egyptens land;\ffra Assyrien vil jeg samle dem.\fJeg vil føre dem til Gileads og Libanons land;\fder skal ikke være plads nok til dem.",
      "number": 10
    },
    {
      "text": "\fHan skal gå igennem trængselshavet;\fslå bølgerne i havet;\falle Nilens strømme udtørres.\fAssyriens hovmod skal undertrykkes;\fEgyptens scepter skal fjernes.",
      "number": 11
    },
    {
      "text": "\fJeg vil styrke dem i JHVH;\fi hans navn skal de vandre,\fsiger JHVH.",
      "number": 12
    }
  ],
  "titles": [
    {
      "text": "Søg tilflugt hos JHVH i stedet for afguderne",
      "verse": 1
    },
    {
      "text": "JHVH vil føre Israel hjem",
      "verse": 3
    }
  ],
  "footnotes": [
    {
      "text": "Det hebraiske ord *fāqad* bruges både om >>hjemsøge<< og >>besøge<< i dette vers. Ordet kan altså både være negativt og positivt.",
      "type": "E",
      "verse": 3,
      "position": 96
    },
    {
      "text": "Ordret >>som af vin<<.",
      "type": "T",
      "verse": 7,
      "position": 70
    },
    {
      "text": "Ordret: >>sønner<<.",
      "type": "T",
      "verse": 7,
      "position": 81
    },
    {
      "text": "En anden mulighed er at oversætte sætningen med >>de skal give deres børn liv<<, eftersom >>børn<< er markeret som objekt i sætningen.",
      "type": "E",
      "verse": 9,
      "position": 99
    },
    {
      "text": "*yeor* skal ikke nødvendigvis forstås som Nilen, men kan forstås mere generelt om floder. Det er klart, at billedet i første omgang henviser til den første exodus fra Egypten, men i anden omgang udvides billedet til en ny exodus fra både Egypten og Assyrien – begge steder med berømte floder.",
      "type": "E",
      "verse": 11,
      "position": 70
    }
  ]
}